{
  "no_wrap": true,
  "text_block_list": [
    {
      "name": "Inari One",
      "text": "¡Guau, de verdad la rifaste! ¡Qué gran botín!\n¡Bien hecho, Jefe!"
    },
    {
      "name": "Inari One",
      "text": "¡Guau, de verdad la rifaste! ¡Qué gran botín!\n¡Bien hecho, Jefe!"
    },
    {
      "name": "Inari One",
      "text": "¡Jeje! ¡Todos son tan lindos como botones! ¡Mi\ncorazón casi no lo aguanta!",
      "choice_data_list": [
        "Asegúrate de cuidarlos bien."
      ]
    },
    {
      "name": "Inari One",
      "text": "¡Lo haré! ¡Gracias de nuevo!"
    },
    {
      "name": "Inari One",
      "text": "¡Bienvenidos a la familia, pequeñines! ¡Vamos a\npasarla genial juntos!"
    },
    {
      "name": "Monólogo",
      "text": "¡Eso no pudo haber ido mejor!"
    }
  ]
}