{
  "no_wrap": true,
  "text_block_list": [
    {
      "name": "Monólogo",
      "text": "El inicio del verano llegó, y poco a poco estoy\nencontrando mi ritmo como entrenadora."
    },
    {
      "name": "Ines Fujin",
      "text": "Haaaaah!",
      "choice_data_list": [
        "¡Tú puedes! ¡Sigue así!",
        "¡Tú puedes! ¡Sigue así!"
      ]
    },
    {
      "name": "Ines Fujin",
      "text": "¡Apenas estoy comenzando! ¡Déjame mostrarte lo que\n<i>realmente puedo </i>hacer!"
    },
    {
      "name": "Ines Fujin",
      "text": "Sin cambios en mi tiempo, ¿eh...?. Creo que\naceleré un poco tarde.",
      "choice_data_list": [
        "¿Quieres dar una vuelta más?",
        "¿Quieres dar una vuelta más?"
      ]
    },
    {
      "name": "Ines Fujin",
      "text": "¿Puedo?"
    },
    {
      "name": "Ines Fujin",
      "text": "Ah, pero... Mmm, creo que me detendré aquí."
    },
    {
      "name": "Ines Fujin",
      "text": "Ya casi se acaba el día y todavía tengo cosas por\nhacer... Sí, continuemos mañana!"
    },
    {
      "name": "Ines Fujin",
      "text": "Voy a guardar el equipo. ¡Nos vemos luego,\nentrenadora!"
    },
    {
      "name": "Monólogo",
      "text": "Se va con una sonrisa, pero no puedo sacudirme esa\nsensación persistente..."
    },
    {
      "name": "Monólogo",
      "text": "Tal vez sea solo yo, pero estoy bastante segura de\nque ella quiere seguir corriendo. ¿Qué podría ser\nmás importante?"
    },
    {
      "name": "Ines Fujin",
      "text": "¿Eh? Pensé que ya habrías regresado.",
      "choice_data_list": [
        "Quería terminar algo."
      ]
    },
    {
      "name": "Ines Fujin",
      "text": "Vale, entonces limpiaré tu área después."
    },
    {
      "name": "Monólogo",
      "text": "Como en piloto automático, empieza a limpiar mi\noficina como si lo hubiera hecho millones de\nveces."
    },
    {
      "name": "Ines Fujin",
      "text": "Veamos... ¡Ah, casi nos quedamos sin papel para\nimpresora! Mejor paso por el almacén antes de\nvolver."
    },
    {
      "name": "Ines Fujin",
      "text": "¡Ups! ¡Tantos conejitos de polvo! ¡Voy a\natraparlos! ♪"
    },
    {
      "name": "Monólogo",
      "text": "Ahora que lo pienso, la oficina siempre está\nlimpia y los suministros nunca se agotan...",
      "choice_data_list": [
        "¿Has estado manteniendo la sala todo este tiempo?!",
        "¿Has estado manteniendo la sala todo este tiempo?!"
      ]
    },
    {
      "name": "Ines Fujin",
      "text": "No pude evitarlo—¡el desorden me irrita! Quiero\nque nuestro espacio compartido esté impecable,\n¿sabes?"
    },
    {
      "name": "Monólogo",
      "text": "No es que no lo aprecie, pero preferiría que ella\nuse este tiempo para entrenar en la pista.",
      "choice_data_list": [
        "¡Lo siento! ¡Me encargaré de la limpieza de ahora\nen adelante!",
        "¡Lo siento! ¡Me encargaré de la limpieza de ahora\nen adelante!"
      ]
    },
    {
      "name": "Ines Fujin",
      "text": "¿Quieres decir... tú sola? ¿Sin ayuda?",
      "choice_data_list": [
        "Sí, no quiero quitarte tiempo de entrenamiento.",
        "Sí, no quiero quitarte tiempo de entrenamiento."
      ]
    },
    {
      "name": "Ines Fujin",
      "text": "¿Quieres decir... tú sola? ¿Sin ayuda?",
      "choice_data_list": [
        "Sí, no quiero quitarte tiempo de entrenamiento.",
        "Sí, no quiero quitarte tiempo de entrenamiento."
      ]
    },
    {
      "name": "Ines Fujin",
      "text": "¿En serio? Bueno... ¡veamos qué tienes! ♪"
    },
    {
      "name": "Monólogo",
      "text": "Solo es limpiar. ¿Qué tan difícil puede ser?"
    },
    {
      "name": "Ines Fujin",
      "text": "¡Ah, el paño de polvo está por allá! Y si buscas\nla escoba y el recogedor, están en la esquina."
    },
    {
      "name": "Ines Fujin",
      "text": "¡Eso va en este estante! ¡Mejor mantener todo\nordenado!"
    },
    {
      "name": "Ines Fujin",
      "text": "Puedes encontrar repuestos allí. Si se agotan,\nsolo pídele al encargado de suministros más.",
      "choice_data_list": [
        "E-esto es mucho más difícil de lo que pensé!",
        "E-esto es mucho más difícil de lo que pensé!"
      ]
    },
    {
      "name": "Ines Fujin",
      "text": "¡Jeje, tú puedes, tú puedes! ♪"
    },
    {
      "name": "Monólogo",
      "text": "Con la guía de Ines Fujin, de alguna forma logré\nterminar la limpieza. Pero...",
      "choice_data_list": [
        "Terminé dependiendo de ti para casi todo..."
      ]
    },
    {
      "name": "Ines Fujin",
      "text": "Hehehe... ¿Impresionada? ¡Este es el resultado de\naños metidos hasta el codo en las tareas! ♪"
    },
    {
      "name": "Ines Fujin",
      "text": "De todos modos, me da pena que hagas todo el\ntrabajo pesado, así que hagámoslo juntos de ahora\nen adelante. Después de todo, ¡este es nuestro\nrincón especial!",
      "choice_data_list": [
        "Sí, señora..."
      ]
    },
    {
      "name": "Ines Fujin",
      "text": "¡Vaya, quita ese ceño! Vamos, preparé té, tomemos\nun descanso."
    },
    {
      "name": "Monólogo",
      "text": "Quise demostrar que ella podía contar conmigo,\npero al final, ella es quien me salva como una\ncaballero con armadura brillante."
    },
    {
      "name": "Monólogo",
      "text": "Quise demostrar que ella podía contar conmigo,\npero al final, ella es quien me salva como una\ncaballero con armadura brillante."
    }
  ]
}