{
  "no_wrap": true,
  "text_block_list": [
    {
      "name": "Nishino Flower",
      "text": "<i>Jaa... jaa...</i>"
    },
    {
      "name": "Nishino Flower",
      "text": "Yo... gané..."
    },
    {
      "name": "Espectadores",
      "text": "Wooooo!"
    },
    {
      "name": "Nishino Flower",
      "text": "...!"
    },
    {
      "name": "Espectadores",
      "text": "¡Guau! ¡Nishino Flower es tan rápida! ¡Es\nincreíble!"
    },
    {
      "name": "Espectadores",
      "text": "¡En serio es una prodigio! ¡Bien hecho, Flower!"
    },
    {
      "name": "Nishino Flower",
      "text": "Phew...",
      "choice_data_list": [
        "¡Flower! ¿Estás bien?!",
        "¡Flower! ¿Estás bien?!"
      ]
    },
    {
      "name": "Nishino Flower",
      "text": "Entrenadora..."
    },
    {
      "name": "Nishino Flower",
      "text": "Yo... ¡Lo logré! ¡Gané!",
      "choice_data_list": [
        "...!"
      ]
    },
    {
      "name": "Nishino Flower",
      "text": "Así que, por favor, no te preocupes tanto."
    },
    {
      "name": "Nishino Flower",
      "text": "Prefiero verte sonreír. Entonces... ¿podrías hacer\neso por mí, por favor?",
      "choice_data_list": [
        "¡Felicidades, Flower!"
      ]
    },
    {
      "name": "Nishino Flower",
      "text": "Gracias... ¡Muchísimas gracias!"
    },
    {
      "name": "Fan A",
      "text": "..."
    },
    {
      "name": "Nishino Flower",
      "text": "...!"
    },
    {
      "name": "Nishino Flower",
      "text": "Oh, esa persona simplemente—",
      "choice_data_list": [
        "Vamos a descansar en la sala de espera."
      ]
    },
    {
      "name": "Nishino Flower",
      "text": "Está bien..."
    },
    {
      "name": "Nishino Flower",
      "text": "(Jeje.)"
    },
    {
      "name": "Fan A",
      "text": "¿Oh, ese es su entrenador? ¡Ahora hay alguien con\nbuen ojo para las corredoras!"
    },
    {
      "name": "Nishino Flower",
      "text": "Estaban elogiando a la Entrenadora."
    },
    {
      "name": "Nishino Flower",
      "text": "(Ganar se siente muy bien. Fue mucho trabajo, pero\nla Entrenadora se veía tan feliz.)"
    },
    {
      "name": "Nishino Flower",
      "text": "(Y gracias a la guía y cuidado de la Entrenadora,\nno me siento tan cansada como después de mi\ncarrera debut.)"
    },
    {
      "name": "Nishino Flower",
      "text": "...Oh."
    },
    {
      "name": "Nishino Flower",
      "text": "(Me preguntaba por qué estaba lista para correr\ntan temprano...)"
    },
    {
      "name": "Nishino Flower",
      "text": "(Pero tal vez sea <i>porque</i> está pasando ahora\nque...)"
    },
    {
      "name": "Nishino Flower",
      "text": "¡Muy bien! ¡Ya tomé una decisión!"
    },
    {
      "name": "Nishino Flower",
      "text": "Entrenadora. Decidí cómo quiero que sea mi próxima\ncarrera."
    },
    {
      "name": "Nishino Flower",
      "text": "¡Quiero volver aquí otra vez, cuando los cerezos\nestén en flor!",
      "choice_data_list": [
        "¿Quieres decir..."
      ]
    },
    {
      "name": "Nishino Flower",
      "text": "Sí. Quiero correr en el Oka Sho y enfrentarme a la\nTriple Tiara!",
      "color_text_info_list": [
        "Oka Sho"
      ]
    },
    {
      "name": "Monólogo",
      "text": "El recorrido de la Triple Tiara comprende tres\ncarreras G1 que solo se pueden correr en el año\nclásico: el Oka Sho, el Japanese Oaks y el Shuka\nSho.",
      "color_text_info_list": [
        "Shuka Sho"
      ]
    },
    {
      "name": "Monólogo",
      "text": "Hoy demostró que puede manejar carreras G1, y su\nforma de correr muestra mucho potencial para su\naño clásico. En ese caso...",
      "choice_data_list": [
        "¡Vale! ¡Será el Oka Sho!"
      ]
    },
    {
      "name": "Nishino Flower",
      "text": "¡Gracias! ¡Haré lo mejor!"
    },
    {
      "name": "Monólogo",
      "text": "Y así, decidimos enfrentar la Triple Tiara\ncorriendo su primera carrera —¡el Oka Sho! Sin\nembargo, hay algo que quiero saber.",
      "choice_data_list": [
        "¿Era este tu plan desde el principio?",
        "¿Era este tu plan desde el principio?"
      ]
    },
    {
      "name": "Monólogo",
      "text": "Muchas Umamusume que corren en el Hanshin Juvenile\nFillies continúan en el recorrido de la Triple\nTiara. Es natural querer desafiar carreras de\nmayor nivel."
    },
    {
      "name": "Monólogo",
      "text": "Recordando, decidir correr el Hanshin Juvenile\nFillies fue una decisión audaz para ella. Tal vez\nsolo pienso en esto porque nunca ha expresado cuál\nes su sueño, pero..."
    },
    {
      "name": "Nishino Flower",
      "text": "Um... Bueno..."
    },
    {
      "name": "Nishino Flower",
      "text": "...¡Te lo diré después del Oka Sho!"
    }
  ]
}