{
  "no_wrap": true,
  "text_block_list": [
    {
      "name": "Umamusume con cintas azules",
      "text": "Hola, Sweep. ¿Cómo estás?"
    },
    {
      "name": "Sweep Tosho",
      "text": "¿Eh? ¿Estás diciendo que me veo mal? En ese caso,\n¡deberías ir a checarte la vista!"
    },
    {
      "name": "Umamusume con cintas azules",
      "text": "Jeje. Sigues igual de siempre. Tu sonrisa es tan\nlinda que hasta resulta molesta."
    },
    {
      "name": "Umamusume con cintas azules",
      "text": "Pero una vez que la carrera termine, creo que\nestarás llorando en una nube de mi polvo."
    },
    {
      "name": "Sweep Tosho",
      "text": "¡Jajaja! ¡Qué buen chiste, viniendo de ti!"
    },
    {
      "name": "Sweep Tosho",
      "text": "Pero no hay forma de que me veas sollozando."
    },
    {
      "name": "Sweep Tosho",
      "text": "Voy a ganar esta competencia y quedaré en la cima,\nsobre todas ustedes."
    },
    {
      "name": "Sweep Tosho",
      "text": "Y entonces voy a sonreír la sonrisa más grande que\njamás hayas visto!"
    },
    {
      "name": "Monólogo",
      "text": "Ya llegó la última competencia del tour Triple\nTiara tour—el Shuka Sho. El telón está a punto de\nlevantarse en la batalla final para convertirte en\nla estrella del año!"
    }
  ]
}